utcnow/__init__.py
utcnow/__main__.py
utcnow/__version__.py
utcnow/__version_data__.py
utcnow/interface.py
utcnow/protobuf/__init__.py
utcnow/py.typed
utcnow-0.3.7.dist-info/LICENSE
utcnow-0.3.7.dist-info/METADATA
utcnow-0.3.7.dist-info/WHEEL
utcnow-0.3.7.dist-info/RECORD
