Metadata-Version: 2.1
Name: utcnow
Version: 0.3.7
Summary: Timestamps as opinionated RFC 3339 (Date and Time on the Internet) formatted strings
Home-page: https://github.com/kalaspuff/utcnow
License: MIT
Keywords: utcnow,utc timestamp,modern timestamp,rfc 3339,rfc3339,timestamp,rfc3339 timestamp,timestamps,date and time on the internet,datetime,zulu time,protobuf,protobuf timestamp
Author: Carl Oscar Aaro
Author-email: hello@carloscar.com
Requires-Python: >=3.7,<4.0
Classifier: Development Status :: 3 - Alpha
Classifier: Intended Audience :: Developers
Classifier: License :: OSI Approved :: MIT License
Classifier: Programming Language :: Python
Classifier: Programming Language :: Python :: 3
Classifier: Programming Language :: Python :: 3.7
Classifier: Programming Language :: Python :: 3.8
Classifier: Programming Language :: Python :: 3.9
Classifier: Programming Language :: Python :: 3.10
Classifier: Programming Language :: Python :: 3.11
Classifier: Programming Language :: Python :: 3.12
Classifier: Topic :: Software Development
Classifier: Topic :: Software Development :: Libraries
Classifier: Typing :: Typed
Provides-Extra: cli
Provides-Extra: protobuf
Requires-Dist: protobuf (>=3.20.0,<5.0.0) ; extra == "protobuf"
Requires-Dist: utcnow-cli (>=1.0.0) ; extra == "cli"
Project-URL: Repository, https://github.com/kalaspuff/utcnow
